maproulette/__init__.py
maproulette/api/__init__.py
maproulette/api/challenge.py
maproulette/api/configuration.py
maproulette/api/errors.py
maproulette/api/maproulette_server.py
maproulette/api/project.py
maproulette/api/query_constants.py
maproulette/api/task.py
maproulette/api/user.py
maproulette/models/__init__.py
maproulette/models/challenge.py
maproulette/models/child_operation.py
maproulette/models/cooperative_work.py
maproulette/models/enums.py
maproulette/models/parent_operation.py
maproulette/models/priority_rule.py
maproulette/models/project.py
maproulette/models/task.py
maproulette-1.8.1.dist-info/LICENSE
maproulette-1.8.1.dist-info/METADATA
maproulette-1.8.1.dist-info/WHEEL
maproulette-1.8.1.dist-info/top_level.txt
maproulette-1.8.1.dist-info/RECORD
