Metadata-Version: 2.1
Name: maproulette
Version: 1.8.1
Summary: A Python API wrapper for MapRoulette
Home-page: https://github.com/osmlab/maproulette-python-client
License: Apache License 2.0
Requires-Python: >=3.6
License-File: LICENSE
Requires-Dist: requests
